fabric_generic_cluster/__init__.py
fabric_generic_cluster/ansible_setup.py
fabric_generic_cluster/builder_compat.py
fabric_generic_cluster/deployment.py
fabric_generic_cluster/models.py
fabric_generic_cluster/network_config.py
fabric_generic_cluster/selinux_management.py
fabric_generic_cluster/ssh_setup.py
fabric_generic_cluster/topology_viewer.py
fabric_generic_cluster/tools/__init__.py
fabric_generic_cluster/tools/topology_summary.py
fabric_generic_cluster-1.0.12.dist-info/licenses/LICENSE
fabric_generic_cluster-1.0.12.dist-info/METADATA
fabric_generic_cluster-1.0.12.dist-info/WHEEL
fabric_generic_cluster-1.0.12.dist-info/entry_points.txt
fabric_generic_cluster-1.0.12.dist-info/top_level.txt
fabric_generic_cluster-1.0.12.dist-info/RECORD
