Metadata-Version: 2.4
Name: fabric-generic-cluster
Version: 1.0.12
Summary: Comprehensive Python framework for managing FABRIC testbed generic clusters and slices
Author-email: Mert Cevik <mcevik@renci.org>
License: MIT
Project-URL: Homepage, https://github.com/mcevik0/fabric-generic-cluster
Project-URL: Documentation, https://github.com/mcevik0/fabric-generic-cluster/blob/main/README.md
Project-URL: Repository, https://github.com/mcevik0/fabric-generic-cluster
Project-URL: Bug Tracker, https://github.com/mcevik0/fabric-generic-cluster/issues
Keywords: fabric,testbed,networking,cloud,infrastructure,dpu,fpga,bluefield
Classifier: Development Status :: 4 - Beta
Classifier: Intended Audience :: Developers
Classifier: Intended Audience :: Science/Research
Classifier: License :: OSI Approved :: MIT License
Classifier: Programming Language :: Python :: 3
Classifier: Programming Language :: Python :: 3.9
Classifier: Programming Language :: Python :: 3.10
Classifier: Programming Language :: Python :: 3.11
Classifier: Programming Language :: Python :: 3.12
Classifier: Topic :: Scientific/Engineering
Classifier: Topic :: System :: Networking
Requires-Python: >=3.9
License-File: LICENSE
Requires-Dist: pydantic>=2.0.0
Requires-Dist: pyyaml>=6.0
Requires-Dist: tabulate>=0.9.0
Requires-Dist: networkx>=3.0
Requires-Dist: matplotlib>=3.7.0
Requires-Dist: fabrictestbed-extensions>=1.4.0
Provides-Extra: dev
Requires-Dist: pytest>=7.0.0; extra == "dev"
Requires-Dist: pytest-cov>=4.0.0; extra == "dev"
Requires-Dist: black>=23.0.0; extra == "dev"
Requires-Dist: flake8>=6.0.0; extra == "dev"
Dynamic: license-file
